nx/viper/__init__.py
nx/viper/application.py
nx/viper/config.py
nx/viper/controller.py
nx/viper/dispatcher.py
nx/viper/interface.py
nx/viper/module.py
nx/viper/service/__init__.py
nx/viper/service/mail.py
nx/viper/service/mysql.py
nx.viper-1.2.4b1.dist-info/LICENSE
nx.viper-1.2.4b1.dist-info/METADATA
nx.viper-1.2.4b1.dist-info/WHEEL
nx.viper-1.2.4b1.dist-info/top_level.txt
nx.viper-1.2.4b1.dist-info/RECORD
