Metadata-Version: 2.1
Name: nx.viper
Version: 1.2.4b1
Summary: Application development framework for twisted.
Home-page: https://github.com/Nixiware/viper
Author: Nixiware
Author-email: contact@nixiware.com
License: MIT
Keywords: nixiware viper twisted
Platform: UNKNOWN
Classifier: Development Status :: 4 - Beta
Classifier: Intended Audience :: Developers
Classifier: Topic :: Software Development :: Libraries :: Application Frameworks
Classifier: License :: OSI Approved :: MIT License
Classifier: Programming Language :: Python :: 3.6
Requires-Dist: twisted
Requires-Dist: autobahn
Requires-Dist: PyMySQL
